{
  "/blog/[i:page]?": {
    "module": "home",
    "controller": "home",
    "name": "home"
  },
  "/admin/add_blog": {
    "module": "addBlogPost",
    "controller": "blog",
    "name": "addBlog"
  },
  "/admin/add_blog/[i:idBlog]": {
    "module": "updateBlogPost",
    "controller": "blog",
    "name": "modifBlog"
  },
  "/admin/delete_blog/[i:idBlog]": {
    "module": "deleteBlogPost",
    "controller": "blog",
    "name": "deleteBlog"
  },
  "/page-[i:page]": {
    "module": "home",
    "controller": "home",
    "name": "home_"
  },
  "/admin": {
    "module": "home",
    "controller": "admin",
    "name": "admin_home"
  },
  "/show-[i:id]": {
    "module": "show",
    "controller": "home",
    "name": "show"
  },
  "/admin/postblogs/[i:page]?": {
    "module": "listBlogPost",
    "controller": "blog",
    "name": "admin_postblogs"
  },

  "/admin/comments/[a:action]/[i:page]?/[i:idBlog]?": {
    "module": "comments",
    "controller": "comment",
    "name": "admin_comments"
  },
  "/admin/delete_com/[i:idCom]": {
    "module": "deleteComment",
    "controller": "comment",
    "name": "delete_comment"
  },
  "/admin/validate_com/[i:idCom]": {
    "module": "validateComment",
    "controller": "comment",
    "name": "validate_comment"
  },
  "/admin/connect": {
    "module": "connectUser",
    "controller": "home",
    "name": "connect"
  },
  "/admin/inscription": {
    "module": "inscription",
    "controller": "admin",
    "name": "admin_inscription"
  },
  "/admin/profile": {
    "module": "profile",
    "controller": "admin",
    "name": "admin_profile",
    "method": "GET"
  },
  "/admin/faker": {
    "module": "faker",
    "controller": "admin",
    "name": "admin_faker",
    "method": "GET"
  }
}